dicom_info-0.1.0.dist-info/licenses/LICENSE
dicominfo/__init__.py
dicom_info-0.1.0.dist-info/METADATA
dicom_info-0.1.0.dist-info/WHEEL
dicom_info-0.1.0.dist-info/entry_points.txt
dicom_info-0.1.0.dist-info/top_level.txt
dicom_info-0.1.0.dist-info/RECORD
