Metadata-Version: 2.4
Name: dicom-info
Version: 0.1.0
Summary: Prints information about DIOCM files.
Requires-Python: >=3.13
License-File: LICENSE
Requires-Dist: pydicom>=3.0.1
Dynamic: license-file
